Workbook
Name LeasUp: #REF!
Name LeasUp: #REF!
Name Master: MASTER_UNIFIED_PORTFOLIO!$A:$AC
Name PayBack: #REF!
Name PayBack: #REF!
Name SBDATA: Dashboard_Data!$AE$1:$AH$20
Name Slicer_Lease_Up_Potential1: #N/A
Name Slicer_Lease_Up_Potential1: #N/A
Name Slicer_Site_classification1: #N/A
Name Slicer_Site_classification1: #N/A
Name Slicer_State1: #N/A
Name Slicer_State1: #N/A
Name Unleased: #REF!
Name Unleased: #REF!

Sheet Executive_Dashboard
B40: STRATEGIC INSIGHTS
B41: Pillar / Strategic Area | D41: Key Metric & Insight | H41: Risk / Opportunity | L41: Recommendation
B42: Pillar 1: Density & Growth | D42: ="High Lease-Up Potential covers " & TEXT(Dashboard_Data!AF7,"0.0%") & " (" & Dashboard_Data!AF5 & " of " & Dashboard_Data!AF4 & ") of candidate sites, concentrated in Urban (100%) and Suburban (97%) markets." -> High Lease-Up Potential covers 70.5% (299 of 424) of candidate sites, concentrated in Urban (100%) and Suburban (97%) markets. | H42: ="Opportunity: dense Urban/Suburban markets show near-universal co-location demand; Rural is a 41% split market." -> Opportunity: dense Urban/Suburban markets show near-universal co-location demand; Rural is a 41% split market. | L42: ="Fast-track sales outreach in Urban/Suburban; treat Rural as case-by-case, not a blanket push." -> Fast-track sales outreach in Urban/Suburban; treat Rural as case-by-case, not a blanket push.
B43: Pillar 2: Structural Profile | D43: ="Dominant structure type is " & Dashboard_Data!AF15 & " at " & TEXT(Dashboard_Data!AF16,"0.0%") & " of the candidate pool." -> Dominant structure type is SST at 60.8% of the candidate pool. | H43: Opportunity: SST towers show the strongest lease-up flag rate of any structure type. | L43: Prioritize SST inventory for near-term co-location sales motion.
B44: Pillar 3: Financial Profile | D44: ="Avg. CAPEX per site: " & TEXT(Dashboard_Data!AF8,"$#,##0") & ". " & TEXT(Dashboard_Data!AF10/Dashboard_Data!AF2,"0%") & " of the portfolio (" & Dashboard_Data!AF10 & " sites) sits in the 10+ year payback tier." -> Avg. CAPEX per site: $71,472. 50% of the portfolio (248 sites) sits in the 10+ year payback tier. | H44: ="Risk: High-Potential sites average " & TEXT(Dashboard_Data!AF13,"0.0") & " yrs anchor-only payback vs. " & TEXT(Dashboard_Data!AF14,"0.0") & " yrs for Low-Potential." -> Risk: High-Potential sites average 12.6 yrs anchor-only payback vs. 4.9 yrs for Low-Potential. | L44: ="Target the 10+ year tier first: " & TEXT(Dashboard_Data!AF12,"0.0%") & " of it is already flagged High-Potential." -> Target the 10+ year tier first: 84.3% of it is already flagged High-Potential.
B45: Pillar 4: Age Profile | D45: ="Site vintage varies across the portfolio (2017–2022 build years); newer, higher-CAPEX sites skew toward the slower anchor-only payback tiers." -> Site vintage varies across the portfolio (2017–2022 build years); newer, higher-CAPEX sites skew toward the slower anchor-only payback tiers. | H45: ="Risk: newer / larger-CAPEX builds take longer to recover on anchor rent alone, before any lease-up is realized." -> Risk: newer / larger-CAPEX builds take longer to recover on anchor rent alone, before any lease-up is realized. | L45: ="Sequence lease-up sales efforts to reach newer, high-CAPEX sites early — they benefit most from a 2nd tenant." -> Sequence lease-up sales efforts to reach newer, high-CAPEX sites early — they benefit most from a 2nd tenant.

Sheet Dashboard_Data
A1: Site Number | B1: Lease_Up_Potential | C1: Site classification | D1: Tower Type | E1: Year Built | F1: Payback_Years | G1: Payback_Category | J1: Classification | K1: High Potential | L1: Low Potential | N1: Payback Category | O1: Site Count | P1: Share of Portfolio | Q1: Lease-Up Potential | R1: Avg Payback (Yrs) | S1: Site Count | U1: Payback Category | V1: High Potential | W1: Low Potential | Y1: Tower Type | Z1: High Potential | AA1: Low Potential | AB1: Total | AE1: KPI
A2: 405 | B2: High Lease Up Potential | C2: Urban | D2: SST | E2: 2022 | F2: 20.634324 | G2: 10+ years Pay Back | J2: Rural | K2: =COUNTIFS($C$2:$C$425,$J2,$B$2:$B$425,"High Lease Up Potential") -> 83 | L2: =COUNTIFS($C$2:$C$425,$J2,$B$2:$B$425,"Low Lease Up Potential") -> 120 | N2: 1-5 years Pay Back | O2: 157 | P2: 0.314 | Q2: High Lease Up Potential | R2: =AVERAGEIFS($F$2:$F$425,$B$2:$B$425,$Q2) -> 12.641557 | S2: =COUNTIFS($B$2:$B$425,$Q2) -> 299 | U2: 1-5 years Pay Back | V2: =COUNTIFS($B$2:$B$425,"High Lease Up Potential",$G$2:$G$425,$U2) -> 47 | W2: =COUNTIFS($B$2:$B$425,"Low Lease Up Potential",$G$2:$G$425,$U2) -> 81 | Y2: SST | Z2: =COUNTIFS($D$2:$D$425,$Y2,$B$2:$B$425,"High Lease Up Potential") -> 195 | AA2: =COUNTIFS($D$2:$D$425,$Y2,$B$2:$B$425,"Low Lease Up Potential") -> 63 | AB2: =Z2+AA2 -> 258 | AE2: Total Sites | AF2: 500
A3: 233 | B3: High Lease Up Potential | C3: Urban | D3: SST | E3: 2019 | F3: 16.872197 | G3: 10+ years Pay Back | J3: Suburban | K3: =COUNTIFS($C$2:$C$425,$J3,$B$2:$B$425,"High Lease Up Potential") -> 179 | L3: =COUNTIFS($C$2:$C$425,$J3,$B$2:$B$425,"Low Lease Up Potential") -> 5 | N3: 5-10 years Pay Back | O3: 95 | P3: 0.19 | Q3: Low Lease Up Potential | R3: =AVERAGEIFS($F$2:$F$425,$B$2:$B$425,$Q3) -> 4.9435001 | S3: =COUNTIFS($B$2:$B$425,$Q3) -> 125 | U3: 5-10 years Pay Back | V3: =COUNTIFS($B$2:$B$425,"High Lease Up Potential",$G$2:$G$425,$U3) -> 43 | W3: =COUNTIFS($B$2:$B$425,"Low Lease Up Potential",$G$2:$G$425,$U3) -> 39 | Y3: Monopole | Z3: =COUNTIFS($D$2:$D$425,$Y3,$B$2:$B$425,"High Lease Up Potential") -> 97 | AA3: =COUNTIFS($D$2:$D$425,$Y3,$B$2:$B$425,"Low Lease Up Potential") -> 52 | AB3: =Z3+AA3 -> 149 | AE3: Already Multi-Tenant Sites | AF3: =AF2-AF4 -> 76
A4: 403 | B4: High Lease Up Potential | C4: Urban | D4: SST | E4: 2021 | F4: 15.13287 | G4: 10+ years Pay Back | J4: Urban | K4: =COUNTIFS($C$2:$C$425,$J4,$B$2:$B$425,"High Lease Up Potential") -> 37 | L4: =COUNTIFS($C$2:$C$425,$J4,$B$2:$B$425,"Low Lease Up Potential") -> 0 | N4: 10+ years Pay Back | O4: 248 | P4: 0.496 | U4: 10+ years Pay Back | V4: =COUNTIFS($B$2:$B$425,"High Lease Up Potential",$G$2:$G$425,$U4) -> 209 | W4: =COUNTIFS($B$2:$B$425,"Low Lease Up Potential",$G$2:$G$425,$U4) -> 5 | Y4: Guyed Tower | Z4: =COUNTIFS($D$2:$D$425,$Y4,$B$2:$B$425,"High Lease Up Potential") -> 3 | AA4: =COUNTIFS($D$2:$D$425,$Y4,$B$2:$B$425,"Low Lease Up Potential") -> 7 | AB4: =Z4+AA4 -> 10 | AE4: Candidate Pool (Unleased) | AF4: 424
A5: 486 | B5: High Lease Up Potential | C5: Urban | D5: Monopole | E5: 2022 | F5: 14.610737 | G5: 10+ years Pay Back | Y5: Stealth - Flagpole | Z5: =COUNTIFS($D$2:$D$425,$Y5,$B$2:$B$425,"High Lease Up Potential") -> 3 | AA5: =COUNTIFS($D$2:$D$425,$Y5,$B$2:$B$425,"Low Lease Up Potential") -> 2 | AB5: =Z5+AA5 -> 5 | AE5: High Potential Sites | AF5: 299
A6: 190 | B6: High Lease Up Potential | C6: Urban | D6: Monopole | E6: 2019 | F6: 11.189251 | G6: 10+ years Pay Back | Y6: Stealth - Monopine | Z6: =COUNTIFS($D$2:$D$425,$Y6,$B$2:$B$425,"High Lease Up Potential") -> 1 | AA6: =COUNTIFS($D$2:$D$425,$Y6,$B$2:$B$425,"Low Lease Up Potential") -> 1 | AB6: =Z6+AA6 -> 2 | AE6: Low Potential Sites | AF6: 125
A7: 130 | B7: High Lease Up Potential | C7: Urban | D7: SST | E7: 2019 | F7: 13.241903 | G7: 10+ years Pay Back | AE7: High Potential Share | AF7: =AF5/AF4 -> 0.70518868
A8: 359 | B8: High Lease Up Potential | C8: Urban | D8: SST | E8: 2021 | F8: 18.365895 | G8: 10+ years Pay Back | AE8: Avg CAPEX / Site (all 500) | AF8: 71472.432
A9: 236 | B9: High Lease Up Potential | C9: Urban | D9: SST | E9: 2019 | F9: 16.299667 | G9: 10+ years Pay Back | AE9: Total Portfolio CAPEX | AF9: 35736216
A10: 271 | B10: High Lease Up Potential | C10: Urban | D10: SST | E10: 2020 | F10: 13.830288 | G10: 10+ years Pay Back | AE10: Sites in 10+ Yr Payback Tier | AF10: 248 | AG10: =AF10/AF2 -> 0.496
A11: 133 | B11: High Lease Up Potential | C11: Urban | D11: SST | E11: 2019 | F11: 18.935691 | G11: 10+ years Pay Back | AE11: ...of which High Potential | AF11: =V4 -> 209
A12: 252 | B12: High Lease Up Potential | C12: Urban | D12: SST | E12: 2019 | F12: 15.500168 | G12: 10+ years Pay Back | AE12: ...share of 10+ tier that is High Potential | AF12: =AF11/AF10 -> 0.84274194
A13: 500 | B13: High Lease Up Potential | C13: Urban | D13: SST | E13: 2022 | F13: 57.80119 | G13: 10+ years Pay Back | AE13: Avg Payback - High Potential (anchor-only) | AF13: =R2 -> 12.641557
A14: 426 | B14: High Lease Up Potential | C14: Urban | D14: SST | E14: 2022 | F14: 59.485143 | G14: 10+ years Pay Back | AE14: Avg Payback - Low Potential (anchor-only) | AF14: =R3 -> 4.9435001
A15: 291 | B15: High Lease Up Potential | C15: Urban | D15: SST | E15: 2021 | F15: 21.66 | G15: 10+ years Pay Back | AE15: Dominant Tower Type (all unleased) | AF15: =INDEX(Y2:Y6,MATCH(MAX(AB2:AB6),AB2:AB6,0)) -> SST
A16: 139 | B16: High Lease Up Potential | C16: Urban | D16: SST | E16: 2019 | F16: 12.978576 | G16: 10+ years Pay Back | AE16: Dominant Tower Type Share | AF16: =MAX(AB2:AB6)/AF4 -> 0.60849057
A17: 496 | B17: High Lease Up Potential | C17: Suburban | D17: SST | E17: 2022 | F17: 14.704861 | G17: 10+ years Pay Back
A18: 310 | B18: High Lease Up Potential | C18: Suburban | D18: SST | E18: 2021 | F18: 15.138167 | G18: 10+ years Pay Back
A19: 345 | B19: High Lease Up Potential | C19: Suburban | D19: SST | E19: 2021 | F19: 17.615048 | G19: 10+ years Pay Back
A20: 388 | B20: High Lease Up Potential | C20: Suburban | D20: SST | E20: 2021 | F20: 15.18832 | G20: 10+ years Pay Back
A21: 425 | B21: High Lease Up Potential | C21: Urban | D21: Monopole | E21: 2022 | F21: 17.17285 | G21: 10+ years Pay Back
A22: 449 | B22: High Lease Up Potential | C22: Suburban | D22: SST | E22: 2022 | F22: 15.279236 | G22: 10+ years Pay Back
A23: 262 | B23: High Lease Up Potential | C23: Urban | D23: SST | E23: 2020 | F23: 21.787917 | G23: 10+ years Pay Back
A24: 259 | B24: High Lease Up Potential | C24: Urban | D24: SST | E24: 2020 | F24: 20.385606 | G24: 10+ years Pay Back
A25: 109 | B25: High Lease Up Potential | C25: Urban | D25: SST | E25: 2018 | F25: 14.489389 | G25: 10+ years Pay Back
A26: 67 | B26: High Lease Up Potential | C26: Urban | D26: SST | E26: 2018 | F26: 14.898315 | G26: 10+ years Pay Back
A27: 58 | B27: High Lease Up Potential | C27: Urban | D27: SST | E27: 2018 | F27: 14.397758 | G27: 10+ years Pay Back
A28: 4 | B28: High Lease Up Potential | C28: Urban | D28: SST | E28: 2017 | F28: 15.35942 | G28: 10+ years Pay Back
... A425: 484 | B425: Low Lease Up Potential | C425: Rural | D425: Stealth - Monopine | E425: 2022 | F425: 11.705729 | G425: 10+ years Pay Back

Sheet MASTER_UNIFIED_PORTFOLIO
A1: Site Number | B1: Site classification | C1: State | D1: Tower Type | E1: Height | F1: Year Built | G1: Anchor Tenant Name | H1: Capex | I1: Additional_Tenant_Count | J1: Stack_Rank | K1: Site Number.1 | L1: Lease_Up_Potential | M1: Leaseup_Score | N1: Site classification.1 | O1: State.1 | P1: Tower Type.1 | Q1: Height.1 | R1: Year Built.1 | S1: Anchor Tenant Name.1 | T1: Capex.1 | U1: Site Number.2 | V1: Site classification.2 | W1: State.2 | X1: Capex.2 | Y1: Anchor Tenant Starting Monthly Rent | Z1: Ground Lease Rent OPEX | AA1: Net_Annual_Income | AB1: Payback_Years | AC1: Payback_Category
A2: 69 | B2: Suburban | C2: OR | D2: SST | E2: 165 | F2: 2018 | G2: Tenant A | H2: 92378 | I2: 0 | J2: 5 | K2: 190 | L2: High Lease Up Potential | M2: 92 | N2: Urban | O2: TX | P2: Monopole | Q2: 205 | R2: 2019 | S2: Tenant A | T2: 87276.16 | U2: 5 | V2: Rural | W2: OR | X2: 20330 | Y2: 950 | Z2: 175 | AA2: 9300 | AB2: 2.1860215 | AC2: 1-5 years Pay Back
A3: 259 | B3: Urban | C3: AZ | D3: SST | E3: 155 | F3: 2020 | G3: Tenant A | H3: 134545 | I3: 0 | J3: 94 | K3: 124 | L3: High Lease Up Potential | M3: 80 | N3: Suburban | O3: TX | P3: SST | Q3: 145 | R3: 2019 | S3: Tenant B | T3: 100567.5 | U3: 94 | V3: Rural | W3: OR | X3: 21810.25 | Y3: 875 | Z3: 350 | AA3: 6300 | AB3: 3.4619444 | AC3: 1-5 years Pay Back
A4: 472 | B4: Suburban | C4: FL | D4: Guyed Tower | E4: 140 | F4: 2022 | G4: Tenant D | H4: 117221.25 | I4: 0 | J4: 61 | K4: 201 | L4: High Lease Up Potential | M4: 84 | N4: Suburban | O4: TX | P4: SST | Q4: 170 | R4: 2019 | S4: Tenant D | T4: 90472.06 | U4: 61 | V4: Rural | W4: AZ | X4: 21848.4 | Y4: 825 | Z4: 375 | AA4: 5400 | AB4: 4.046 | AC4: 1-5 years Pay Back
A5: 365 | B5: Rural | C5: AZ | D5: SST | E5: 155 | F5: 2021 | G5: Tenant B | H5: 33969.6 | I5: 0 | J5: 206 | K5: 84 | L5: High Lease Up Potential | M5: 71 | N5: Suburban | O5: FL | P5: Monopole | Q5: 170 | R5: 2018 | S5: Tenant C | T5: 88603.84 | U5: 206 | V5: Rural | W5: PA | X5: 21913.38 | Y5: 950 | Z5: 350 | AA5: 7200 | AB5: 3.043525 | AC5: 1-5 years Pay Back
A6: 78 | B6: Suburban | C6: FL | D6: Monopole | E6: 140 | F6: 2018 | G6: Tenant B | H6: 99832.95 | I6: 0 | J6: 223 | K6: 466 | L6: High Lease Up Potential | M6: 70 | N6: Rural | O6: PA | P6: SST | Q6: 200 | R6: 2022 | S6: Tenant C | T6: 32921.25 | U6: 223 | V6: Rural | W6: AZ | X6: 22600.6 | Y6: 950 | Z6: 225 | AA6: 8700 | AB6: 2.5977701 | AC6: 1-5 years Pay Back
A7: 148 | B7: Rural | C7: AZ | D7: SST | E7: 145 | F7: 2019 | G7: Tenant C | H7: 39775.32 | I7: 0 | J7: 81 | K7: 307 | L7: High Lease Up Potential | M7: 82 | N7: Suburban | O7: AZ | P7: Monopole | Q7: 185 | R7: 2021 | S7: Tenant C | T7: 114187.2 | U7: 81 | V7: Rural | W7: PA | X7: 22632.19 | Y7: 950 | Z7: 300 | AA7: 7800 | AB7: 2.9015628 | AC7: 1-5 years Pay Back
A8: 360 | B8: Rural | C8: PA | D8: SST | E8: 215 | F8: 2021 | G8: Tenant B | H8: 42669.6 | I8: 0 | J8: 45 | K8: 400 | L8: High Lease Up Potential | M8: 85 | N8: Suburban | O8: PA | P8: SST | Q8: 230 | R8: 2021 | S8: Tenant A | T8: 104485.2 | U8: 45 | V8: Rural | W8: OR | X8: 22866 | Y8: 950 | Z8: 275 | AA8: 8100 | AB8: 2.822963 | AC8: 1-5 years Pay Back
A9: 343 | B9: Rural | C9: FL | D9: Monopole | E9: 205 | F9: 2021 | G9: Tenant B | H9: 33500.4 | I9: 0 | J9: 42 | K9: 43 | L9: High Lease Up Potential | M9: 86 | N9: Urban | O9: TX | P9: Monopole | Q9: 160 | R9: 2018 | S9: Tenant C | T9: 108223.5 | U9: 42 | V9: Rural | W9: PA | X9: 23124.4 | Y9: 950 | Z9: 300 | AA9: 7800 | AB9: 2.9646667 | AC9: 1-5 years Pay Back
A10: 373 | B10: Rural | C10: PA | D10: Monopole | E10: 165 | F10: 2021 | G10: Tenant C | H10: 28458 | I10: 0 | J10: 46 | K10: 284 | L10: High Lease Up Potential | M10: 85 | N10: Suburban | O10: OR | P10: SST | Q10: 220 | R10: 2021 | S10: Tenant A | T10: 104505.52 | U10: 46 | V10: Rural | W10: PA | X10: 23549.4 | Y10: 950 | Z10: 275 | AA10: 8100 | AB10: 2.9073333 | AC10: 1-5 years Pay Back
A11: 161 | B11: Rural | C11: AZ | D11: SST | E11: 160 | F11: 2019 | G11: Tenant C | H11: 37293.3 | I11: 0 | J11: 234 | K11: 381 | L11: High Lease Up Potential | M11: 70 | N11: Rural | O11: OR | P11: SST | Q11: 225 | R11: 2021 | S11: Tenant B | T11: 46520.4 | U11: 234 | V11: Rural | W11: AZ | X11: 23569.7 | Y11: 975 | Z11: 225 | AA11: 9000 | AB11: 2.6188556 | AC11: 1-5 years Pay Back
A12: 491 | B12: Rural | C12: OR | D12: Monopole | E12: 225 | F12: 2022 | G12: Tenant B | H12: 29931.25 | I12: 0 | J12: 63 | K12: 202 | L12: High Lease Up Potential | M12: 84 | N12: Suburban | O12: TX | P12: SST | Q12: 175 | R12: 2019 | S12: Tenant B | T12: 107986.44 | U12: 63 | V12: Rural | W12: PA | X12: 23647.52 | Y12: 975 | Z12: 350 | AA12: 7500 | AB12: 3.1530027 | AC12: 1-5 years Pay Back
A13: 463 | B13: Rural | C13: PA | D13: SST | E13: 180 | F13: 2022 | G13: Tenant D | H13: 37098.75 | I13: 0 | J13: 214 | K13: 44 | L13: High Lease Up Potential | M13: 71 | N13: Suburban | O13: PA | P13: Monopole | Q13: 185 | R13: 2018 | S13: Tenant A | T13: 110680.5 | U13: 214 | V13: Rural | W13: TX | X13: 23819.4 | Y13: 975 | Z13: 350 | AA13: 7500 | AB13: 3.17592 | AC13: 1-5 years Pay Back
... A18: 208 | B18: Rural | C18: TX | D18: Monopole | E18: 215 | F18: 2019 | G18: Tenant D | H18: 26345.52 | I18: 0 | J18: 25 | K18: 67 | L18: High Lease Up Potential | M18: 89 | N18: Urban | O18: FL | P18: SST | Q18: 225 | R18: 2018 | S18: Tenant A | T18: 98328.88 | U18: 25 | V18: Rural | W18: TX | X18: 24532 | Y18: 875 | Z18: 200 | AA18: 8100 | AB18: 3.028642 | AC18: 1-5 years Pay Back
A19: 159 | B19: Rural | C19: PA | D19: Monopole | E19: 140 | F19: 2019 | G19: Tenant D | H19: 25215.300000000003 | I19: 0 | J19: 83 | K19: 268 | L19: High Lease Up Potential | M19: 82 | N19: Suburban | O19: PA | P19: SST | Q19: 225 | R19: 2020 | S19: Tenant A | T19: 115236.25 | U19: 83 | V19: Rural | W19: TX | X19: 24696.31 | Y19: 825 | Z19: 225 | AA19: 7200 | AB19: 3.4300431 | AC19: 1-5 years Pay Back
A20: 268 | B20: Suburban | C20: PA | D20: SST | E20: 225 | F20: 2020 | G20: Tenant A | H20: 115236.25 | I20: 0 | J20: 404 | K20: 267 | L20: Low Lease Up Potential | M20: 56 | N20: Rural | O20: OR | P20: SST | Q20: 110 | R20: 2020 | S20: Tenant C | T20: 38785 | U20: 404 | V20: Rural | W20: OR | X20: 24715.2 | Y20: 975 | Z20: 350 | AA20: 7500 | AB20: 3.29536 | AC20: 1-5 years Pay Back
A21: 276 | B21: Suburban | C21: FL | D21: SST | E21: 195 | F21: 2020 | G21: Tenant D | H21: 122871.25 | I21: 0 | J21: 32 | K21: 75 | L21: High Lease Up Potential | M21: 87 | N21: Urban | O21: AZ | P21: SST | Q21: 130 | R21: 2018 | S21: Tenant B | T21: 95874.46 | U21: 32 | V21: Rural | W21: FL | X21: 24868 | Y21: 950 | Z21: 325 | AA21: 7500 | AB21: 3.3157333 | AC21: 1-5 years Pay Back
A22: 448 | B22: Rural | C22: TX | D22: SST | E22: 140 | F22: 2022 | G22: Tenant C | H22: 48842.07 | I22: 0 | J22: 213 | K22: 111 | L22: High Lease Up Potential | M22: 71 | N22: Suburban | O22: OR | P22: Monopole | Q22: 190 | R22: 2018 | S22: Tenant D | T22: 108838.8 | U22: 213 | V22: Rural | W22: OR | X22: 25100.9 | Y22: 975 | Z22: 275 | AA22: 8400 | AB22: 2.9882024 | AC22: 1-5 years Pay Back
A23: 223 | B23: Rural | C23: AZ | D23: Monopole | E23: 170 | F23: 2019 | G23: Tenant A | H23: 22600.6 | I23: 0 | J23: 399 | K23: 128 | L23: Low Lease Up Potential | M23: 56 | N23: Rural | O23: FL | P23: SST | Q23: 115 | R23: 2019 | S23: Tenant D | T23: 36090.88 | U23: 399 | V23: Rural | W23: TX | X23: 25496.4 | Y23: 950 | Z23: 200 | AA23: 9000 | AB23: 2.8329333 | AC23: 1-5 years Pay Back
A24: 73 | B24: Suburban | C24: FL | D24: Monopole | E24: 140 | F24: 2018 | G24: Tenant A | H24: 84035.7 | I24: 0 | J24: 6 | K24: 130 | L24: High Lease Up Potential | M24: 92 | N24: Urban | O24: OR | P24: SST | Q24: 220 | R24: 2019 | S24: Tenant C | T24: 95341.7 | U24: 6 | V24: Rural | W24: AZ | X24: 25682 | Y24: 875 | AA24: 10500 | AB24: 2.4459048 | AC24: 1-5 years Pay Back
A25: 379 | B25: Suburban | C25: FL | D25: SST | E25: 100 | F25: 2021 | G25: Tenant A | H25: 104562 | I25: 0 | J25: 357 | K25: 105 | L25: Low Lease Up Potential | M25: 61 | N25: Rural | O25: PA | P25: SST | Q25: 160 | R25: 2018 | S25: Tenant D | T25: 33072.9 | U25: 357 | V25: Rural | W25: AZ | X25: 25762.8 | Y25: 950 | Z25: 250 | AA25: 8400 | AB25: 3.067 | AC25: 1-5 years Pay Back
A26: 246 | B26: Rural | C26: PA | D26: SST | E26: 200 | F26: 2019 | G26: Tenant C | H26: 37101.06 | I26: 0 | J26: 288 | K26: 65 | L26: High Lease Up Potential | M26: 67 | N26: Suburban | O26: PA | P26: Monopole | Q26: 155 | R26: 2018 | S26: Tenant A | T26: 107742.12 | U26: 288 | V26: Rural | W26: PA | X26: 25816.8 | Y26: 950 | Z26: 325 | AA26: 7500 | AB26: 3.44224 | AC26: 1-5 years Pay Back
A27: 471 | B27: Suburban | C27: OR | D27: SST | E27: 185 | F27: 2022 | G27: Tenant D | H27: 133112.5 | I27: 0 | J27: 60 | K27: 390 | L27: High Lease Up Potential | M27: 85 | N27: Suburban | O27: FL | P27: SST | Q27: 205 | R27: 2021 | S27: Tenant B | T27: 130543.2 | U27: 60 | V27: Rural | W27: PA | X27: 26023.92 | Y27: 975 | Z27: 200 | AA27: 9300 | AB27: 2.798271 | AC27: 1-5 years Pay Back
A28: 248 | B28: Rural | C28: OR | D28: Monopole | E28: 160 | F28: 2019 | G28: Tenant C | H28: 38049.48 | I28: 0 | J28: 401 | K28: 121 | L28: Low Lease Up Potential | M28: 56 | N28: Rural | O28: PA | P28: SST | Q28: 115 | R28: 2019 | S28: Tenant D | T28: 37370.3 | U28: 401 | V28: Rural | W28: OR | X28: 26030.4 | Y28: 825 | Z28: 350 | AA28: 5700 | AB28: 4.5667368 | AC28: 1-5 years Pay Back
A29: 242 | B29: Urban | C29: FL | D29: Stealth - Flagpole | E29: 160 | F29: 2019 | G29: Tenant C | H29: 100640.64 | I29: 0 | J29: 92 | K29: 239 | L29: High Lease Up Potential | M29: 81 | N29: Urban | O29: FL | P29: SST | Q29: 110 | R29: 2019 | S29: Tenant D | T29: 90693 | U29: 92 | V29: Rural | W29: AZ | X29: 26047.67 | Y29: 975 | Z29: 325 | AA29: 7800 | AB29: 3.3394449 | AC29: 1-5 years Pay Back
B30: N/A | C30: N/A | L30: Pending Review | U30: 465 | V30: Rural | W30: OR | X30: 26068.75 | Y30: 950 | Z30: 250 | AA30: 8400 | AB30: 3.1034226 | AC30: 1-5 years Pay Back
A31: 307 | B31: Suburban | C31: AZ | D31: Monopole | E31: 185 | F31: 2021 | G31: Tenant C | H31: 114187.2 | I31: 0 | J31: 150 | K31: 116 | L31: High Lease Up Potential | M31: 76 | N31: Suburban | O31: FL | P31: SST | Q31: 160 | R31: 2018 | S31: Tenant A | T31: 89028.16 | U31: 150 | V31: Rural | W31: PA | X31: 26139.24 | Y31: 950 | Z31: 350 | AA31: 7200 | AB31: 3.63045 | AC31: 1-5 years Pay Back
A32: 390 | B32: Suburban | C32: FL | D32: SST | E32: 205 | F32: 2021 | G32: Tenant B | H32: 130543.2 | I32: 0 | J32: 208 | K32: 138 | L32: High Lease Up Potential | M32: 71 | N32: Suburban | O32: TX | P32: Monopole | Q32: 115 | R32: 2019 | S32: Tenant A | T32: 92045.16 | U32: 208 | V32: Rural | W32: TX | X32: 26345.52 | Y32: 825 | Z32: 175 | AA32: 7800 | AB32: 3.3776308 | AC32: 1-5 years Pay Back
A33: 202 | B33: Suburban | C33: TX | D33: SST | E33: 175 | F33: 2019 | G33: Tenant B | H33: 107986.44 | I33: 0 | J33: 87 | K33: 435 | L33: High Lease Up Potential | M33: 82 | N33: Suburban | O33: PA | P33: SST | Q33: 160 | R33: 2022 | S33: Tenant C | T33: 121287.84 | U33: 87 | V33: Rural | W33: AZ | X33: 26408.17 | Y33: 975 | Z33: 350 | AA33: 7500 | AB33: 3.5210893 | AC33: 1-5 years Pay Back
A34: 402 | B34: Rural | C34: OR | D34: Monopole | E34: 165 | F34: 2021 | G34: Tenant D | H34: 33697.2 | I34: 0 | J34: 311 | K34: 170 | L34: Low Lease Up Potential | M34: 64 | N34: Rural | O34: FL | P34: SST | Q34: 195 | R34: 2019 | S34: Tenant D | T34: 30138.48 | U34: 311 | V34: Rural | W34: TX | X34: 26619.6 | Y34: 875 | Z34: 375 | AA34: 6000 | AB34: 4.4366 | AC34: 1-5 years Pay Back
A35: 388 | B35: Suburban | C35: TX | D35: SST | E35: 225 | F35: 2021 | G35: Tenant D | H35: 113912.4 | I35: 0 | J35: 308 | K35: 55 | L35: Low Lease Up Potential | M35: 64 | N35: Rural | O35: TX | P35: Monopole | Q35: 230 | R35: 2018 | S35: Tenant D | T35: 28861.63 | U35: 308 | V35: Rural | W35: AZ | X35: 26750.4 | Y35: 875 | Z35: 175 | AA35: 8400 | AB35: 3.1845714 | AC35: 1-5 years Pay Back
A36: 454 | B36: Suburban | C36: OR | D36: SST | E36: 200 | F36: 2022 | G36: Tenant B | H36: 108716.01 | I36: 0 | J36: 56 | K36: 478 | L36: High Lease Up Potential | M36: 85 | N36: Suburban | O36: TX | P36: Monopole | Q36: 220 | R36: 2022 | S36: Tenant D | T36: 124838.75 | U36: 56 | V36: Rural | W36: TX | X36: 26795.6 | Y36: 825 | Z36: 275 | AA36: 6600 | AB36: 4.0599394 | AC36: 1-5 years Pay Back
A37: 127 | B37: Rural | C37: PA | D37: Monopole | E37: 170 | F37: 2019 | G37: Tenant D | H37: 28017.92 | I37: 0 | J37: 13 | K37: 426 | L37: High Lease Up Potential | M37: 92 | N37: Urban | O37: PA | P37: SST | Q37: 185 | R37: 2022 | S37: Tenant B | T37: 124918.8 | U37: 13 | V37: Rural | W37: OR | X37: 27072 | Y37: 950 | Z37: 225 | AA37: 8700 | AB37: 3.1117241 | AC37: 1-5 years Pay Back
B38: N/A | C38: N/A | L38: Pending Review | U38: 497 | V38: Rural | W38: PA | X38: 27095 | Y38: 875 | Z38: 325 | AA38: 6600 | AB38: 4.105303 | AC38: 1-5 years Pay Back
A39: 267 | B39: Rural | C39: OR | D39: SST | E39: 110 | F39: 2020 | G39: Tenant C | H39: 38785 | I39: 0 | J39: 146 | K39: 178 | L39: High Lease Up Potential | M39: 77 | N39: Suburban | O39: OR | P39: Monopole | Q39: 205 | R39: 2019 | S39: Tenant C | T39: 108794.88 | U39: 146 | V39: Rural | W39: OR | X39: 27133.88 | Y39: 950 | Z39: 250 | AA39: 8400 | AB39: 3.2302238 | AC39: 1-5 years Pay Back
B40: N/A | C40: N/A | L40: Pending Review | U40: 431 | V40: Rural | W40: OR | X40: 27138.72 | Y40: 875 | Z40: 300 | AA40: 6900 | AB40: 3.9331478 | AC40: 1-5 years Pay Back
A41: 228 | B41: Rural | C41: OR | D41: SST | E41: 185 | F41: 2019 | G41: Tenant A | H41: 36587.16 | I41: 0 | J41: 342 | K41: 218 | L41: Low Lease Up Potential | M41: 62 | N41: Rural | O41: FL | P41: Monopole | Q41: 205 | R41: 2019 | S41: Tenant D | T41: 35850.6 | U41: 342 | V41: Rural | W41: PA | X41: 27154.8 | Y41: 975 | Z41: 175 | AA41: 9600 | AB41: 2.828625 | AC41: 1-5 years Pay Back
A42: 284 | B42: Suburban | C42: OR | D42: SST | E42: 220 | F42: 2021 | G42: Tenant A | H42: 104505.52 | I42: 0 | J42: 245 | K42: 196 | L42: High Lease Up Potential | M42: 69 | N42: Urban | O42: FL | P42: Stealth - Flagpole | Q42: 165 | R42: 2019 | S42: Tenant C | T42: 106497.14 | U42: 245 | V42: Rural | W42: TX | X42: 27254.88 | Y42: 975 | Z42: 325 | AA42: 7800 | AB42: 3.4942154 | AC42: 1-5 years Pay Back
A43: 322 | B43: Suburban | C43: OR | D43: Monopole | E43: 200 | F43: 2021 | G43: Tenant A | H43: 105723.6 | I43: 0 | J43: 350 | K43: 81 | L43: Low Lease Up Potential | M43: 61 | N43: Rural | O43: PA | P43: SST | Q43: 180 | R43: 2018 | S43: Tenant A | T43: 22632.19 | U43: 350 | V43: Rural | W43: OR | X43: 27264 | Y43: 950 | Z43: 325 | AA43: 7500 | AB43: 3.6352 | AC43: 1-5 years Pay Back
A44: 197 | B44: Suburban | C44: FL | D44: SST | E44: 95 | F44: 2019 | G44: Tenant B | H44: 115262.28 | I44: 0 | J44: 397 | K44: 414 | L44: Low Lease Up Potential | M44: 56 | N44: Rural | O44: PA | P44: Guyed Tower | Q44: 150 | R44: 2022 | S44: Tenant A | T44: 33428.94 | U44: 397 | V44: Rural | W44: AZ | X44: 27312 | Y44: 975 | Z44: 175 | AA44: 9600 | AB44: 2.845 | AC44: 1-5 years Pay Back
A45: 189 | B45: Suburban | C45: FL | D45: Monopole | E45: 135 | F45: 2019 | G45: Tenant D | H45: 112124.68 | I45: 0 | J45: 394 | K45: 141 | L45: Low Lease Up Potential | M45: 56 | N45: Rural | O45: PA | P45: SST | Q45: 105 | R45: 2019 | S45: Tenant D | T45: 24252.8 | U45: 394 | V45: Rural | W45: PA | X45: 27364.8 | Y45: 975 | Z45: 325 | AA45: 7800 | AB45: 3.5083077 | AC45: 1-5 years Pay Back
A46: 196 | B46: Urban | C46: FL | D46: Stealth - Flagpole | E46: 165 | F46: 2019 | G46: Tenant C | H46: 106497.14 | I46: 0 | J46: 396 | K46: 132 | L46: Low Lease Up Potential | M46: 56 | N46: Rural | O46: OR | P46: SST | Q46: 115 | R46: 2019 | S46: Tenant A | T46: 31024.08 | U46: 396 | V46: Rural | W46: TX | X46: 27524.4 | Y46: 950 | Z46: 200 | AA46: 9000 | AB46: 3.0582667 | AC46: 1-5 years Pay Back
A47: 317 | B47: Rural | C47: PA | D47: Monopole | E47: 135 | F47: 2021 | G47: Tenant B | H47: 27866.4 | I47: 0 | J47: 39 | K47: 172 | L47: High Lease Up Potential | M47: 87 | N47: Suburban | O47: AZ | P47: SST | Q47: 215 | R47: 2019 | S47: Tenant C | T47: 115790.16 | U47: 39 | V47: Rural | W47: OR | X47: 27865.95 | Y47: 950 | Z47: 175 | AA47: 9300 | AB47: 2.9963387 | AC47: 1-5 years Pay Back
A48: 475 | B48: Suburban | C48: AZ | D48: SST | E48: 170 | F48: 2022 | G48: Tenant D | H48: 101576.25 | I48: 0 | J48: 317 | K48: 228 | L48: Low Lease Up Potential | M48: 64 | N48: Rural | O48: OR | P48: SST | Q48: 185 | R48: 2019 | S48: Tenant A | T48: 36587.16 | U48: 317 | V48: Rural | W48: PA | X48: 27866.4 | Y48: 875 | Z48: 350 | AA48: 6300 | AB48: 4.4232381 | AC48: 1-5 years Pay Back
A49: 367 | B49: Rural | C49: TX | D49: SST | E49: 165 | F49: 2021 | G49: Tenant A | H49: 31366.8 | I49: 0 | J49: 103 | K49: 265 | L49: High Lease Up Potential | M49: 80 | N49: Suburban | O49: TX | P49: SST | Q49: 145 | R49: 2020 | S49: Tenant D | T49: 130821.25 | U49: 103 | V49: Rural | W49: OR | X49: 27925.36 | Y49: 950 | Z49: 325 | AA49: 7500 | AB49: 3.7233813 | AC49: 1-5 years Pay Back
A50: 94 | B50: Rural | C50: OR | D50: Monopole | E50: 180 | F50: 2018 | G50: Tenant B | H50: 21810.25 | I50: 0 | J50: 127 | K50: 299 | L50: High Lease Up Potential | M50: 79 | N50: Suburban | O50: AZ | P50: SST | Q50: 105 | R50: 2021 | S50: Tenant B | T50: 121714.8 | U50: 127 | V50: Rural | W50: PA | X50: 28017.92 | Y50: 825 | Z50: 375 | AA50: 5400 | AB50: 5.1885037 | AC50: 5-10 years Pay Back
A51: 269 | B51: Suburban | C51: AZ | D51: SST | E51: 130 | F51: 2020 | G51: Tenant C | H51: 107877.5 | I51: 0 | J51: 147 | K51: 489 | L51: High Lease Up Potential | M51: 77 | N51: Suburban | O51: PA | P51: Monopole | Q51: 160 | R51: 2022 | S51: Tenant C | T51: 113731.25 | U51: 147 | V51: Rural | W51: TX | X51: 28147.9 | Y51: 875 | Z51: 350 | AA51: 6300 | AB51: 4.4679206 | AC51: 1-5 years Pay Back
A52: 35 | B52: Suburban | C52: TX | D52: SST | E52: 145 | F52: 2017 | G52: Tenant C | H52: 90675 | I52: 0 | J52: 373 | K52: 183 | L52: Low Lease Up Potential | M52: 59 | N52: Rural | O52: FL | P52: Monopole | Q52: 195 | R52: 2019 | S52: Tenant C | T52: 34563.42 | U52: 373 | V52: Rural | W52: PA | X52: 28458 | Y52: 975 | Z52: 225 | AA52: 9000 | AB52: 3.162 | AC52: 1-5 years Pay Back
... A54: 219 | B54: Rural | C54: TX | D54: SST | E54: 110 | F54: 2019 | G54: Tenant D | H54: 31851.94 | I54: 0 | J54: 88 | K54: 283 | L54: High Lease Up Potential | M54: 82 | N54: Suburban | O54: FL | P54: SST | Q54: 185 | R54: 2021 | S54: Tenant C | T54: 122922.96 | U54: 88 | V54: Rural | W54: TX | X54: 28656.66 | Y54: 950 | Z54: 300 | AA54: 7800 | AB54: 3.6739308 | AC54: 1-5 years Pay Back
A55: 383 | B55: Suburban | C55: TX | D55: Monopole | E55: 245 | F55: 2021 | G55: Tenant A | H55: 117771.6 | I55: 0 | J55: 413 | K55: 273 | L55: Low Lease Up Potential | M55: 55 | N55: Rural | O55: FL | P55: Monopole | Q55: 140 | R55: 2020 | S55: Tenant D | T55: 43681.25 | U55: 413 | V55: Rural | W55: PA | X55: 28665.15 | Y55: 825 | AA55: 9900 | AB55: 2.8954697 | AC55: 1-5 years Pay Back
A56: 452 | B56: Urban | C56: FL | D56: SST | E56: 105 | F56: 2022 | G56: Tenant A | H56: 110757.81 | I56: 0 | J56: 55 | K56: 287 | L56: High Lease Up Potential | M56: 85 | N56: Suburban | O56: FL | P56: SST | Q56: 215 | R56: 2021 | S56: Tenant A | T56: 121669.2 | U56: 55 | V56: Rural | W56: TX | X56: 28861.63 | Y56: 825 | Z56: 325 | AA56: 6000 | AB56: 4.8102717 | AC56: 1-5 years Pay Back
A57: 250 | B57: Suburban | C57: AZ | D57: Monopole | E57: 95 | F57: 2019 | G57: Tenant B | H57: 107901.72 | I57: 0 | J57: 145 | K57: 327 | L57: High Lease Up Potential | M57: 77 | N57: Suburban | O57: FL | P57: Monopole | Q57: 175 | R57: 2021 | S57: Tenant C | T57: 103276.8 | U57: 145 | V57: Rural | W57: FL | X57: 28924.22 | Y57: 875 | Z57: 325 | AA57: 6600 | AB57: 4.3824576 | AC57: 1-5 years Pay Back
A58: 226 | B58: Suburban | C58: TX | D58: Monopole | E58: 245 | F58: 2019 | G58: Tenant B | H58: 114874.32 | I58: 0 | J58: 193 | K58: 480 | L58: High Lease Up Potential | M58: 72 | N58: Rural | O58: AZ | P58: SST | Q58: 180 | R58: 2022 | S58: Tenant D | T58: 30970 | U58: 193 | V58: Rural | W58: PA | X58: 29115.02 | Y58: 975 | Z58: 325 | AA58: 7800 | AB58: 3.7326949 | AC58: 1-5 years Pay Back
A59: 183 | B59: Rural | C59: FL | D59: Monopole | E59: 195 | F59: 2019 | G59: Tenant C | H59: 34563.42 | I59: 0 | J59: 391 | K59: 45 | L59: Low Lease Up Potential | M59: 56 | N59: Rural | O59: OR | P59: Monopole | Q59: 190 | R59: 2018 | S59: Tenant A | T59: 22866 | U59: 391 | V59: Rural | W59: OR | X59: 29400 | Y59: 875 | Z59: 325 | AA59: 6600 | AB59: 4.4545455 | AC59: 1-5 years Pay Back
A60: 265 | B60: Suburban | C60: TX | D60: SST | E60: 145 | F60: 2020 | G60: Tenant D | H60: 130821.25 | I60: 0 | J60: 29 | K60: 372 | L60: High Lease Up Potential | M60: 88 | N60: Urban | O60: FL | P60: Guyed Tower | Q60: 200 | R60: 2021 | S60: Tenant A | T60: 112762.8 | U60: 29 | V60: Rural | W60: PA | X60: 29622 | Y60: 975 | Z60: 350 | AA60: 7500 | AB60: 3.9496 | AC60: 1-5 years Pay Back
A61: 488 | B61: Suburban | C61: FL | D61: Monopole | E61: 245 | F61: 2022 | G61: Tenant A | H61: 123923.75 | I61: 0 | J61: 323 | K61: 313 | L61: Low Lease Up Potential | M61: 63 | N61: Rural | O61: PA | P61: SST | Q61: 140 | R61: 2021 | S61: Tenant D | T61: 30336 | U61: 323 | V61: Rural | W61: AZ | X61: 29636.4 | Y61: 825 | Z61: 200 | AA61: 7500 | AB61: 3.95152 | AC61: 1-5 years Pay Back
A62: 339 | B62: Suburban | C62: FL | D62: SST | E62: 195 | F62: 2021 | G62: Tenant A | H62: 111172.8 | I62: 0 | J62: 254 | K62: 493 | L62: High Lease Up Potential | M62: 68 | N62: Rural | O62: TX | P62: SST | Q62: 145 | R62: 2022 | S62: Tenant A | T62: 46676.25 | U62: 254 | V62: Rural | W62: TX | X62: 29835.82 | Y62: 950 | Z62: 225 | AA62: 8700 | AB62: 3.4294046 | AC62: 1-5 years Pay Back
B63: N/A | C63: N/A | L63: Pending Review | U63: 427 | V63: Rural | W63: TX | X63: 29895.15 | Y63: 950 | Z63: 275 | AA63: 8100 | AB63: 3.6907593 | AC63: 1-5 years Pay Back
B64: N/A | C64: N/A | L64: Pending Review | U64: 491 | V64: Rural | W64: OR | X64: 29931.25 | Y64: 875 | Z64: 325 | AA64: 6600 | AB64: 4.5350379 | AC64: 1-5 years Pay Back
A65: 482 | B65: Rural | C65: PA | D65: SST | E65: 110 | F65: 2022 | G65: Tenant B | H65: 32543.75 | I65: 0 | J65: 321 | K65: 166 | L65: Low Lease Up Potential | M65: 64 | N65: Suburban | O65: OR | P65: Guyed Tower | Q65: 95 | R65: 2019 | S65: Tenant A | T65: 101584.8 | U65: 321 | V65: Rural | W65: FL | X65: 30102 | Y65: 950 | AA65: 11400 | AB65: 2.6405263 | AC65: 1-5 years Pay Back
A66: 41 | B66: Urban | C66: TX | D66: SST | E66: 140 | F66: 2018 | G66: Tenant A | H66: 114636.9 | I66: 0 | J66: 328 | K66: 389 | L66: Low Lease Up Potential | M66: 63 | N66: Rural | O66: PA | P66: SST | Q66: 135 | R66: 2021 | S66: Tenant D | T66: 39584.4 | U66: 328 | V66: Rural | W66: PA | X66: 30178.8 | Y66: 975 | Z66: 300 | AA66: 8100 | AB66: 3.7257778 | AC66: 1-5 years Pay Back
A67: 24 | B67: Suburban | C67: PA | D67: SST | E67: 120 | F67: 2017 | G67: Tenant A | H67: 97806 | I67: 0 | J67: 66 | K67: 280 | L67: High Lease Up Potential | M67: 83 | N67: Suburban | O67: TX | P67: SST | Q67: 150 | R67: 2021 | S67: Tenant A | T67: 94686.74 | U67: 66 | V67: Rural | W67: FL | X67: 30245.28 | Y67: 825 | Z67: 400 | AA67: 5100 | AB67: 5.9304471 | AC67: 5-10 years Pay Back
A68: 351 | B68: Suburban | C68: AZ | D68: Monopole | E68: 230 | F68: 2021 | G68: Tenant C | H68: 126897.6 | I68: 0 | J68: 256 | K68: 461 | L68: High Lease Up Potential | M68: 68 | N68: Rural | O68: TX | P68: SST | Q68: 125 | R68: 2022 | S68: Tenant C | T68: 48907.26 | U68: 256 | V68: Rural | W68: PA | X68: 30325 | Y68: 875 | Z68: 350 | AA68: 6300 | AB68: 4.8134921 | AC68: 1-5 years Pay Back
A69: 435 | B69: Suburban | C69: PA | D69: SST | E69: 160 | F69: 2022 | G69: Tenant C | H69: 121287.84 | I69: 0 | J69: 313 | K69: 162 | L69: Low Lease Up Potential | M69: 64 | N69: Rural | O69: PA | P69: SST | Q69: 175 | R69: 2019 | S69: Tenant D | T69: 34003.74 | U69: 313 | V69: Rural | W69: PA | X69: 30336 | Y69: 825 | Z69: 325 | AA69: 6000 | AB69: 5.056 | AC69: 5-10 years Pay Back
A70: 168 | B70: Suburban | C70: OR | D70: SST | E70: 90 | F70: 2019 | G70: Tenant C | H70: 113217.54 | I70: 0 | J70: 185 | K70: 362 | L70: High Lease Up Potential | M70: 73 | N70: Suburban | O70: FL | P70: Monopole | Q70: 140 | R70: 2021 | S70: Tenant C | T70: 116605.2 | U70: 185 | V70: Rural | W70: TX | X70: 30366.88 | Y70: 825 | Z70: 325 | AA70: 6000 | AB70: 5.0611467 | AC70: 5-10 years Pay Back
A71: 130 | B71: Urban | C71: OR | D71: SST | E71: 220 | F71: 2019 | G71: Tenant C | H71: 95341.7 | I71: 0 | J71: 333 | K71: 99 | L71: Low Lease Up Potential | M71: 63 | N71: Suburban | O71: OR | P71: Monopole | Q71: 90 | R71: 2018 | S71: Tenant A | T71: 94621.28 | U71: 333 | V71: Rural | W71: FL | X71: 30398.4 | Y71: 975 | Z71: 350 | AA71: 7500 | AB71: 4.05312 | AC71: 1-5 years Pay Back
A72: 222 | B72: Rural | C72: TX | D72: Monopole | E72: 110 | F72: 2019 | G72: Tenant D | H72: 41977.060000000005 | I72: 0 | J72: 192 | K72: 314 | L72: High Lease Up Potential | M72: 72 | N72: Rural | O72: AZ | P72: SST | Q72: 165 | R72: 2021 | S72: Tenant A | T72: 30674.4 | U72: 192 | V72: Rural | W72: OR | X72: 30542.84 | Y72: 950 | Z72: 200 | AA72: 9000 | AB72: 3.3936489 | AC72: 1-5 years Pay Back
A73: 289 | B73: Rural | C73: PA | D73: Monopole | E73: 175 | F73: 2021 | G73: Tenant B | H73: 41454 | I73: 0 | J73: 247 | K73: 422 | L73: High Lease Up Potential | M73: 69 | N73: Suburban | O73: PA | P73: Monopole | Q73: 110 | R73: 2022 | S73: Tenant C | T73: 109419.57 | U73: 247 | V73: Rural | W73: TX | X73: 30556.44 | Y73: 825 | Z73: 250 | AA73: 6900 | AB73: 4.4284696 | AC73: 1-5 years Pay Back
A74: 122 | B74: Suburban | C74: FL | D74: Monopole | E74: 185 | F74: 2019 | G74: Tenant C | H74: 102498 | I74: 0 | J74: 227 | K74: 336 | L74: High Lease Up Potential | M74: 70 | N74: Rural | O74: OR | P74: SST | Q74: 225 | R74: 2021 | S74: Tenant A | T74: 38684.4 | U74: 227 | V74: Rural | W74: AZ | X74: 30646.08 | Y74: 975 | Z74: 325 | AA74: 7800 | AB74: 3.9289846 | AC74: 1-5 years Pay Back
A75: 455 | B75: Rural | C75: PA | D75: SST | E75: 145 | F75: 2022 | G75: Tenant B | H75: 49142.19 | I75: 0 | J75: 314 | K75: 123 | L75: Low Lease Up Potential | M75: 64 | N75: Rural | O75: TX | P75: Monopole | Q75: 160 | R75: 2019 | S75: Tenant A | T75: 35134.56 | U75: 314 | V75: Rural | W75: AZ | X75: 30674.4 | Y75: 950 | Z75: 325 | AA75: 7500 | AB75: 4.08992 | AC75: 1-5 years Pay Back
B76: N/A | C76: N/A | L76: Pending Review | U76: 480 | V76: Rural | W76: AZ | X76: 30970 | Y76: 825 | Z76: 325 | AA76: 6000 | AB76: 5.1616667 | AC76: 5-10 years Pay Back
A77: 142 | B77: Suburban | C77: OR | D77: Monopole | E77: 175 | F77: 2019 | G77: Tenant A | H77: 104130.16 | I77: 0 | J77: 132 | K77: 446 | L77: High Lease Up Potential | M77: 78 | N77: Suburban | O77: OR | P77: SST | Q77: 145 | R77: 2022 | S77: Tenant A | T77: 101815.71 | U77: 132 | V77: Rural | W77: OR | X77: 31024.08 | Y77: 950 | Z77: 275 | AA77: 8100 | AB77: 3.8301333 | AC77: 1-5 years Pay Back
A78: 316 | B78: Suburban | C78: AZ | D78: SST | E78: 195 | F78: 2021 | G78: Tenant C | H78: 121504.8 | I78: 0 | J78: 38 | K78: 41 | L78: High Lease Up Potential | M78: 87 | N78: Urban | O78: TX | P78: SST | Q78: 140 | R78: 2018 | S78: Tenant A | T78: 114636.9 | U78: 38 | V78: Rural | W78: PA | X78: 31061.1 | Y78: 875 | Z78: 250 | AA78: 7500 | AB78: 4.14148 | AC78: 1-5 years Pay Back
A79: 440 | B79: Suburban | C79: PA | D79: Monopole | E79: 90 | F79: 2022 | G79: Tenant B | H79: 129393.54 | I79: 0 | J79: 417 | K79: 474 | L79: Low Lease Up Potential | M79: 54 | N79: Rural | O79: PA | P79: Monopole | Q79: 95 | R79: 2022 | S79: Tenant D | T79: 34130 | U79: 417 | V79: Rural | W79: OR | X79: 31079.64 | Y79: 950 | Z79: 200 | AA79: 9000 | AB79: 3.4532933 | AC79: 1-5 years Pay Back
A80: 453 | B80: Suburban | C80: FL | D80: SST | E80: 135 | F80: 2022 | G80: Tenant A | H80: 110011.2 | I80: 0 | J80: 419 | K80: 92 | L80: Low Lease Up Potential | M80: 53 | N80: Rural | O80: AZ | P80: Monopole | Q80: 105 | R80: 2018 | S80: Tenant C | T80: 26047.67 | U80: 419 | V80: Rural | W80: TX | X80: 31114.08 | Y80: 825 | Z80: 225 | AA80: 7200 | AB80: 4.3214 | AC80: 1-5 years Pay Back
A81: 67 | B81: Urban | C81: FL | D81: SST | E81: 225 | F81: 2018 | G81: Tenant A | H81: 98328.88 | I81: 0 | J81: 74 | K81: 392 | L81: High Lease Up Potential | M81: 82 | N81: Suburban | O81: PA | P81: SST | Q81: 195 | R81: 2021 | S81: Tenant C | T81: 103060.8 | U81: 74 | V81: Rural | W81: TX | X81: 31138.64 | Y81: 825 | Z81: 375 | AA81: 5400 | AB81: 5.7664148 | AC81: 5-10 years Pay Back
A82: 210 | B82: Suburban | C82: TX | D82: Monopole | E82: 205 | F82: 2019 | G82: Tenant D | H82: 117630.7 | I82: 0 | J82: 140 | K82: 64 | L82: High Lease Up Potential | M82: 77 | N82: Suburban | O82: AZ | P82: SST | Q82: 125 | R82: 2018 | S82: Tenant C | T82: 85485.92 | U82: 140 | V82: Rural | W82: AZ | X82: 31352.68 | Y82: 975 | Z82: 175 | AA82: 9600 | AB82: 3.2659042 | AC82: 1-5 years Pay Back
A83: 438 | B83: Suburban | C83: FL | D83: SST | E83: 240 | F83: 2022 | G83: Tenant B | H83: 108171.12 | I83: 0 | J83: 367 | K83: 199 | L83: Low Lease Up Potential | M83: 60 | N83: Rural | O83: PA | P83: SST | Q83: 120 | R83: 2019 | S83: Tenant A | T83: 35300.12 | U83: 367 | V83: Rural | W83: TX | X83: 31366.8 | Y83: 950 | Z83: 325 | AA83: 7500 | AB83: 4.18224 | AC83: 1-5 years Pay Back
A84: 445 | B84: Rural | C84: TX | D84: SST | E84: 210 | F84: 2022 | G84: Tenant C | H84: 32845.92 | I84: 0 | J84: 418 | K84: 432 | L84: Low Lease Up Potential | M84: 54 | N84: Rural | O84: FL | P84: Monopole | Q84: 110 | R84: 2022 | S84: Tenant D | T84: 41217.3 | U84: 418 | V84: Rural | W84: FL | X84: 31531.05 | Y84: 825 | Z84: 200 | AA84: 7500 | AB84: 4.20414 | AC84: 1-5 years Pay Back
A85: 52 | B85: Suburban | C85: FL | D85: SST | E85: 150 | F85: 2018 | G85: Tenant A | H85: 105608.88 | I85: 0 | J85: 221 | K85: 285 | L85: High Lease Up Potential | M85: 70 | N85: Rural | O85: OR | P85: SST | Q85: 215 | R85: 2021 | S85: Tenant D | T85: 30799.18 | U85: 221 | V85: Rural | W85: FL | X85: 31720.68 | Y85: 950 | Z85: 275 | AA85: 8100 | AB85: 3.9161333 | AC85: 1-5 years Pay Back
A86: 26 | B86: Suburban | C86: PA | D86: SST | E86: 190 | F86: 2017 | G86: Tenant B | H86: 105910 | I86: 0 | J86: 219 | K86: 288 | L86: High Lease Up Potential | M86: 70 | N86: Rural | O86: PA | P86: SST | Q86: 215 | R86: 2021 | S86: Tenant A | T86: 25816.8 | U86: 219 | V86: Rural | W86: TX | X86: 31851.94 | Y86: 825 | Z86: 175 | AA86: 7800 | AB86: 4.0835821 | AC86: 1-5 years Pay Back
A87: 245 | B87: Rural | C87: TX | D87: Monopole | E87: 175 | F87: 2019 | G87: Tenant C | H87: 27254.88 | I87: 0 | J87: 195 | K87: 458 | L87: High Lease Up Potential | M87: 72 | N87: Rural | O87: AZ | P87: SST | Q87: 180 | R87: 2022 | S87: Tenant C | T87: 34838.52 | U87: 195 | V87: Rural | W87: PA | X87: 32039.28 | Y87: 875 | Z87: 375 | AA87: 6000 | AB87: 5.33988 | AC87: 5-10 years Pay Back
B88: N/A | C88: N/A | L88: Pending Review | U88: 483 | V88: Rural | W88: PA | X88: 32045 | Y88: 950 | Z88: 275 | AA88: 8100 | AB88: 3.9561728 | AC88: 1-5 years Pay Back
A89: 330 | B89: Suburban | C89: FL | D89: SST | E89: 125 | F89: 2021 | G89: Tenant C | H89: 131312.4 | I89: 0 | J89: 253 | K89: 430 | L89: High Lease Up Potential | M89: 68 | N89: Rural | O89: TX | P89: SST | Q89: 140 | R89: 2022 | S89: Tenant A | T89: 43512.48 | U89: 253 | V89: Rural | W89: PA | X89: 32231.42 | Y89: 825 | Z89: 150 | AA89: 8100 | AB89: 3.9791877 | AC89: 1-5 years Pay Back
B90: N/A | C90: N/A | L90: Pending Review | U90: 443 | V90: Rural | W90: PA | X90: 32262.9 | Y90: 975 | Z90: 225 | AA90: 9000 | AB90: 3.5847667 | AC90: 1-5 years Pay Back
B91: N/A | C91: N/A | L91: Pending Review | U91: 473 | V91: Rural | W91: PA | X91: 32447.5 | Y91: 825 | Z91: 300 | AA91: 6300 | AB91: 5.1503968 | AC91: 5-10 years Pay Back
B92: N/A | C92: N/A | L92: Pending Review | U92: 482 | V92: Rural | W92: PA | X92: 32543.75 | Y92: 875 | Z92: 250 | AA92: 7500 | AB92: 4.3391667 | AC92: 1-5 years Pay Back
A93: 151 | B93: Suburban | C93: PA | D93: Monopole | E93: 100 | F93: 2019 | G93: Tenant B | H93: 98223.84 | I93: 0 | J93: 182 | K93: 434 | L93: High Lease Up Potential | M93: 73 | N93: Suburban | O93: FL | P93: Monopole | Q93: 120 | R93: 2022 | S93: Tenant A | T93: 104253.57 | U93: 182 | V93: Rural | W93: OR | X93: 32636.34 | Y93: 825 | Z93: 350 | AA93: 5700 | AB93: 5.7256737 | AC93: 5-10 years Pay Back
A94: 374 | B94: Rural | C94: PA | D94: Monopole | E94: 175 | F94: 2021 | G94: Tenant C | H94: 35860.8 | I94: 0 | J94: 257 | K94: 278 | L94: High Lease Up Potential | M94: 67 | N94: Rural | O94: FL | P94: SST | Q94: 185 | R94: 2021 | S94: Tenant D | T94: 23819.48 | U94: 257 | V94: Rural | W94: PA | X94: 32822.5 | Y94: 875 | Z94: 175 | AA94: 8400 | AB94: 3.9074405 | AC94: 1-5 years Pay Back
A95: 237 | B95: Rural | C95: OR | D95: SST | E95: 220 | F95: 2019 | G95: Tenant A | H95: 42262.56 | I95: 0 | J95: 27 | K95: 4 | L95: High Lease Up Potential | M95: 89 | N95: Urban | O95: FL | P95: SST | Q95: 200 | R95: 2017 | S95: Tenant C | T95: 105980 | U95: 27 | V95: Rural | W95: AZ | X95: 32826 | Y95: 950 | Z95: 225 | AA95: 8700 | AB95: 3.7731034 | AC95: 1-5 years Pay Back
B96: N/A | C96: N/A | L96: Pending Review | U96: 445 | V96: Rural | W96: TX | X96: 32845.92 | Y96: 975 | Z96: 175 | AA96: 9600 | AB96: 3.42145 | AC96: 1-5 years Pay Back
A97: 409 | B97: Rural | C97: PA | D97: SST | E97: 185 | F97: 2022 | G97: Tenant D | H97: 37256.7 | I97: 0 | J97: 107 | K97: 158 | L97: High Lease Up Potential | M97: 79 | N97: Suburban | O97: FL | P97: SST | Q97: 195 | R97: 2019 | S97: Tenant D | T97: 87548.04 | U97: 107 | V97: Rural | W97: TX | X97: 32906.64 | Y97: 875 | Z97: 275 | AA97: 7200 | AB97: 4.5703667 | AC97: 1-5 years Pay Back
B98: N/A | C98: N/A | L98: Pending Review | U98: 466 | V98: Rural | W98: PA | X98: 32921.25 | Y98: 975 | Z98: 375 | AA98: 7200 | AB98: 4.5723958 | AC98: 1-5 years Pay Back
A99: 382 | B99: Rural | C99: PA | D99: SST | E99: 140 | F99: 2021 | G99: Tenant B | H99: 37566 | I99: 0 | J99: 105 | K99: 40 | L99: High Lease Up Potential | M99: 79 | N99: Suburban | O99: FL | P99: SST | Q99: 210 | R99: 2018 | S99: Tenant B | T99: 85397.52 | U99: 105 | V99: Rural | W99: PA | X99: 33072.9 | Y99: 825 | AA99: 9900 | AB99: 3.340697 | AC99: 1-5 years Pay Back
A100: 277 | B100: Suburban | C100: FL | D100: SST | E100: 180 | F100: 2021 | G100: Tenant C | H100: 108067.94 | I100: 0 | J100: 33 | K100: 176 | L100: High Lease Up Potential | M100: 87 | N100: Suburban | O100: AZ | P100: SST | Q100: 210 | R100: 2019 | S100: Tenant C | T100: 95966.04 | U100: 33 | V100: Rural | W100: OR | X100: 33341 | Y100: 975 | Z100: 325 | AA100: 7800 | AB100: 4.2744872 | AC100: 1-5 years Pay Back
A101: 381 | B101: Rural | C101: OR | D101: SST | E101: 225 | F101: 2021 | G101: Tenant B | H101: 46520.4 | I101: 0 | J101: 49 | K101: 438 | L101: High Lease Up Potential | M101: 85 | N101: Suburban | O101: FL | P101: SST | Q101: 240 | R101: 2022 | S101: Tenant B | T101: 108171.12 | U101: 49 | V101: Rural | W101: AZ | X101: 33360.6 | Y101: 950 | Z101: 325 | AA101: 7500 | AB101: 4.44808 | AC101: 1-5 years Pay Back
A102: 391 | B102: Rural | C102: OR | D102: Monopole | E102: 120 | F102: 2021 | G102: Tenant B | H102: 29400 | I102: 0 | J102: 414 | K102: 417 | L102: Low Lease Up Potential | M102: 54 | N102: Rural | O102: OR | P102: Monopole | Q102: 90 | R102: 2022 | S102: Tenant A | T102: 31079.64 | U102: 414 | V102: Rural | W102: PA | X102: 33428.94 | Y102: 950 | Z102: 350 | AA102: 7200 | AB102: 4.6429083 | AC102: 1-5 years Pay Back
A103: 80 | B103: Rural | C103: OR | D103: SST | E103: 170 | F103: 2018 | G103: Tenant B | H103: 40431.3 | I103: 0 | J103: 377 | K103: 467 | L103: Low Lease Up Potential | M103: 59 | N103: Rural | O103: TX | P103: Monopole | Q103: 95 | R103: 2022 | S103: Tenant B | T103: 47280 | U103: 377 | V103: Rural | W103: PA | X103: 33474 | Y103: 975 | Z103: 300 | AA103: 8100 | AB103: 4.1325926 | AC103: 1-5 years Pay Back
A104: 253 | B104: Rural | C104: PA | D104: SST | E104: 155 | F104: 2019 | G104: Tenant D | H104: 32231.42 | I104: 0 | J104: 343 | K104: 374 | L104: Low Lease Up Potential | M104: 62 | N104: Rural | O104: PA | P104: Monopole | Q104: 175 | R104: 2021 | S104: Tenant C | T104: 35860.8 | U104: 343 | V104: Rural | W104: FL | X104: 33500.4 | Y104: 875 | Z104: 150 | AA104: 8700 | AB104: 3.8506207 | AC104: 1-5 years Pay Back
A105: 487 | B105: Suburban | C105: FL | D105: SST | E105: 135 | F105: 2022 | G105: Tenant B | H105: 133226.25 | I105: 0 | J105: 370 | K105: 321 | L105: Low Lease Up Potential | M105: 59 | N105: Rural | O105: FL | P105: SST | Q105: 110 | R105: 2021 | S105: Tenant A | T105: 30102 | U105: 370 | V105: Rural | W105: OR | X105: 33554.4 | Y105: 825 | Z105: 350 | AA105: 5700 | AB105: 5.8867368 | AC105: 5-10 years Pay Back
...

Sheet Pivots
A1: Density & Growth
A2: Sum of Site Number | B2: Column Labels
A3: Row Labels | B3: High Lease Up Potential | C3: Low Lease Up Potential | D3: (blank) | E3: Grand Total
A4: Rural | B4: 41779 | C4: 15294 | E4: 57073
A5: Suburban | B5: 26809 | C5: 18007 | E5: 44816
A6: Urban | B6: 5654 | C6: 3813 | E6: 9467
A7: (blank)
A8: Grand Total | B8: 74242 | C8: 37114 | E8: 111356
A9: Structural Profile
A10: Height | B10: (All)
A12: Sum of Site Number | B12: Column Labels
A13: Row Labels | B13: High Lease Up Potential | C13: Low Lease Up Potential | D13: Grand Total
A14: Guyed Tower | B14: 1952 | C14: 1103 | D14: 3055
A15: Monopole | B15: 23663 | C15: 15395 | D15: 39058
A16: SST | B16: 47076 | C16: 20420 | D16: 67496
A17: Stealth - Flagpole | B17: 703 | C17: 196 | D17: 899
A18: Stealth - Monopine | B18: 848 | D18: 848
A19: Grand Total | B19: 74242 | C19: 37114 | D19: 111356
A22: Financial Profile
A23: Row Labels | B23: Count of Site Number | C23: Average of Capex | D23: Average of Net_Annual_Income
A24: 1-5 years Pay Back | B24: 137 | C24: 74251.142 | D24: 8136.3057
A25: 10+ years Pay Back | B25: 212 | C25: 78400.671 | D25: 7219.3548
A26: 5-10 years Pay Back | B26: 75 | C26: 65241.6 | D26: 7092.6316
A27: Grand Total | B27: 424 | C27: 74759.61 | D27: 7483.2
A29: Age Profile
A30: Sum of Site Number | B30: Column Labels
A31: Row Labels | B31: High Lease Up Potential | C31: Low Lease Up Potential | D31: Grand Total
A32: 2015-2019 | B32: 21338 | C32: 7063 | D32: 28401
A33: 2020-2025 | B33: 52904 | C33: 30051 | D33: 82955
A34: Grand Total | B34: 74242 | C34: 37114 | D34: 111356

Sheet Calc
A2: Total Unleased Sites | B2: =COUNTA(UnLeased!A2:A500) -> 424 | C2: ="TOTAL UNLEASED SITES" & CHAR(10) & TEXT(COUNTA(UnLeased!C2:C500), "#,##0") -> TOTAL UNLEASED SITES 424
A3: High Potential Sites | B3: =COUNTIF(LeaseUp!C2:C500, "High Lease Up Potential") -> 299 | C3: ="HIGH POTENTIAL SITES" & CHAR(10) & TEXT(COUNTIF(LeaseUp!C2:C500, "High Lease Up Potential"), "#,##0") -> HIGH POTENTIAL SITES 299
A4: Low Potential Sites | B4: =COUNTIF(LeaseUp!C2:C500, "Low Lease Up Potential") -> 125 | C4: ="LOW POTENTIAL SITES" & CHAR(10) & TEXT(COUNTIF(LeaseUp!C2:C500, "Low Lease Up Potential"), "#,##0") -> LOW POTENTIAL SITES 125
A5: High Potential Share | B5: =TEXT(COUNTIF(LeaseUp!C2:C500, "High Lease Up Potential")/COUNTA(LeaseUp!A2:A500), "0.0%") -> 70.5% | C5: ="HIGH POTENTIAL SHARE" & CHAR(10) & TEXT(COUNTIF(LeaseUp!C2:C500, "High Lease Up Potential")/COUNTA(LeaseUp!A2:A500), "0.0%") -> HIGH POTENTIAL SHARE 70.5%
A6: Total Portfolio Capex | B6: =TEXT(SUM(PayBack!D2:D501), "$#,##0") -> $35,736,216 | C6: ="TOTAL PORTFOLIO CAPEX" & CHAR(10) & TEXT(SUM(PayBack!D2:D501), "$#,##0") -> TOTAL PORTFOLIO CAPEX $35,736,216
A7: Avg Payback Period | B7: =TEXT(AVERAGE(PayBack!H2:H501), "0.0") & " Yrs" -> 10.2 Yrs | C7: ="AVG PAYBACK PERIOD" & CHAR(10) & TEXT(AVERAGE(PayBack!H2:H501), "0.0") & " Yrs" -> AVG PAYBACK PERIOD 10.2 Yrs
A8: 1-5 Yr Payback | B8: =TEXT(COUNTIF(PayBack!I2:I500, "1-5 years Pay Back"), "#,##0") -> 157 | C8: ="1-5 YR PAYBACK SITES" & CHAR(10) & TEXT(COUNTIF(PayBack!I2:I500, "1-5 years Pay Back"), "#,##0") -> 1-5 YR PAYBACK SITES 157
A9: 5-10 yr Payback | B9: =TEXT(COUNTIF(PayBack!I2:I500, "5-10 years Pay Back"), "#,##0") -> 95 | C9: ="5-10 YR PAYBACK SITES" & CHAR(10) & TEXT(COUNTIF(PayBack!I2:I500, "5-10 years Pay Back"), "#,##0") -> 5-10 YR PAYBACK SITES 95
A10: 10 + Yr Payback | B10: =TEXT(COUNTIF(PayBack!I2:I500, "10+ years Pay Back"), "#,##0") -> 247 | C10: ="10+ YR PAYBACK SITES" & CHAR(10) & TEXT(COUNTIF(PayBack!I2:I500, "10+ years Pay Back"), "#,##0") -> 10+ YR PAYBACK SITES 247

Sheet UnLeased
A1: Site Number | B1: Site classification | C1: State | D1: Tower Type | E1: Height | F1: Year Built | G1: Anchor Tenant Name | H1: Capex | I1: Additional_Tenant_Count | M1: =SUM(H2:H425) -> 30793446
A2: 7 | B2: Suburban | C2: AZ | D2: SST | E2: 185 | F2: 2017 | G2: Tenant B | H2: 82296 | I2: 0
A3: 20 | B3: Suburban | C3: AZ | D3: Monopole | E3: 120 | F3: 2017 | G3: Tenant A | H3: 99848 | I3: 0
A4: 40 | B4: Suburban | C4: FL | D4: SST | E4: 210 | F4: 2018 | G4: Tenant B | H4: 85397.52 | I4: 0
A5: 68 | B5: Rural | C5: PA | D5: Monopole | E5: 195 | F5: 2018 | G5: Tenant D | H5: 37968.32 | I5: 0
A6: 69 | B6: Suburban | C6: OR | D6: SST | E6: 165 | F6: 2018 | G6: Tenant A | H6: 92378 | I6: 0
A7: 73 | B7: Suburban | C7: FL | D7: Monopole | E7: 140 | F7: 2018 | G7: Tenant A | H7: 84035.7 | I7: 0
A8: 76 | B8: Suburban | C8: OR | D8: SST | E8: 215 | F8: 2018 | G8: Tenant A | H8: 96011.45 | I8: 0
A9: 81 | B9: Rural | C9: PA | D9: SST | E9: 180 | F9: 2018 | G9: Tenant A | H9: 22632.19 | I9: 0
A10: 90 | B10: Rural | C10: FL | D10: Monopole | E10: 195 | F10: 2018 | G10: Tenant A | H10: 40276.09 | I10: 0
A11: 101 | B11: Urban | C11: FL | D11: Stealth - Flagpole | E11: 240 | F11: 2018 | G11: Tenant A | H11: 106028 | I11: 0
A12: 112 | B12: Suburban | C12: PA | D12: Monopole | E12: 135 | F12: 2018 | G12: Tenant C | H12: 108379.69 | I12: 0
A13: 118 | B13: Rural | C13: PA | D13: SST | E13: 210 | F13: 2018 | G13: Tenant A | H13: 26424.3 | I13: 0
... A425: 496 | B425: Suburban | C425: TX | D425: SST | E425: 225 | F425: 2022 | G425: Tenant A | H425: 105875 | I425: 0

Sheet LeaseUp
A1: Stack_Rank | B1: Site Number | C1: Lease_Up_Potential | D1: Leaseup_Score | E1: Site classification | F1: State | G1: Tower Type | H1: Height | I1: Year Built | J1: Anchor Tenant Name | K1: Capex
A2: 1 | B2: 405 | C2: High Lease Up Potential | D2: 100 | E2: Urban | F2: TX | G2: SST | H2: 225 | I2: 2022 | J2: Tenant B | K2: 129996.24
A3: 2 | B3: 233 | C3: High Lease Up Potential | D3: 97 | E3: Urban | F3: TX | G3: SST | H3: 210 | I3: 2019 | J3: Tenant B | K3: 101233.18
A4: 3 | B4: 403 | C4: High Lease Up Potential | D4: 97 | E4: Urban | F4: AZ | G4: SST | H4: 175 | I4: 2021 | J4: Tenant A | K4: 104416.8
A5: 4 | B5: 486 | C5: High Lease Up Potential | D5: 95 | E5: Urban | F5: TX | G5: Monopole | H5: 205 | I5: 2022 | J5: Tenant C | K5: 113963.75
A6: 5 | B6: 190 | C6: High Lease Up Potential | D6: 92 | E6: Urban | F6: TX | G6: Monopole | H6: 205 | I6: 2019 | J6: Tenant A | K6: 87276.16
A7: 6 | B7: 130 | C7: High Lease Up Potential | D7: 92 | E7: Urban | F7: OR | G7: SST | H7: 220 | I7: 2019 | J7: Tenant C | K7: 95341.7
A8: 7 | B8: 359 | C8: High Lease Up Potential | D8: 92 | E8: Urban | F8: PA | G8: SST | H8: 165 | I8: 2021 | J8: Tenant D | K8: 104685.6
A9: 8 | B9: 236 | C9: High Lease Up Potential | D9: 92 | E9: Urban | F9: OR | G9: SST | H9: 220 | I9: 2019 | J9: Tenant A | K9: 107577.8
A10: 9 | B10: 271 | C10: High Lease Up Potential | D10: 92 | E10: Urban | F10: FL | G10: SST | H10: 225 | I10: 2020 | J10: Tenant C | K10: 107876.25
A11: 10 | B11: 133 | C11: High Lease Up Potential | D11: 92 | E11: Urban | F11: OR | G11: SST | H11: 215 | I11: 2019 | J11: Tenant B | K11: 107933.44
A12: 11 | B12: 252 | C12: High Lease Up Potential | D12: 92 | E12: Urban | F12: FL | G12: SST | H12: 215 | I12: 2019 | J12: Tenant C | K12: 116251.26
A13: 12 | B13: 500 | C13: High Lease Up Potential | D13: 92 | E13: Urban | F13: FL | G13: SST | H13: 170 | I13: 2022 | J13: Tenant B | K13: 121382.5
... A425: 424 | B425: 484 | C425: Low Lease Up Potential | D425: 39 | E425: Rural | F425: OR | G425: Stealth - Monopine | H425: 100 | I425: 2022 | J425: Tenant A | K425: 112375

Sheet PayBack
A1: Site Number | B1: Site classification | C1: State | D1: Capex | E1: Anchor Tenant Starting Monthly Rent | F1: Ground Lease Rent OPEX | G1: Net_Annual_Income | H1: Payback_Years | I1: Payback_Category
A2: 5 | B2: Rural | C2: OR | D2: 20330 | E2: 950 | F2: 175 | G2: 9300 | H2: 2.1860215 | I2: 1-5 years Pay Back
A3: 153 | B3: Rural | C3: OR | D3: 21612.96 | E3: 975 | F3: 325 | G3: 7800 | H3: 2.7708923 | I3: 1-5 years Pay Back
A4: 94 | B4: Rural | C4: OR | D4: 21810.25 | E4: 875 | F4: 350 | G4: 6300 | H4: 3.4619444 | I4: 1-5 years Pay Back
A5: 61 | B5: Rural | C5: AZ | D5: 21848.4 | E5: 825 | F5: 375 | G5: 5400 | H5: 4.046 | I5: 1-5 years Pay Back
A6: 206 | B6: Rural | C6: PA | D6: 21913.38 | E6: 950 | F6: 350 | G6: 7200 | H6: 3.043525 | I6: 1-5 years Pay Back
A7: 223 | B7: Rural | C7: AZ | D7: 22600.6 | E7: 950 | F7: 225 | G7: 8700 | H7: 2.5977701 | I7: 1-5 years Pay Back
A8: 81 | B8: Rural | C8: PA | D8: 22632.19 | E8: 950 | F8: 300 | G8: 7800 | H8: 2.9015628 | I8: 1-5 years Pay Back
A9: 45 | B9: Rural | C9: OR | D9: 22866 | E9: 950 | F9: 275 | G9: 8100 | H9: 2.822963 | I9: 1-5 years Pay Back
A10: 42 | B10: Rural | C10: PA | D10: 23124.4 | E10: 950 | F10: 300 | G10: 7800 | H10: 2.9646667 | I10: 1-5 years Pay Back
A11: 46 | B11: Rural | C11: PA | D11: 23549.4 | E11: 950 | F11: 275 | G11: 8100 | H11: 2.9073333 | I11: 1-5 years Pay Back
A12: 234 | B12: Rural | C12: AZ | D12: 23569.7 | E12: 975 | F12: 225 | G12: 9000 | H12: 2.6188556 | I12: 1-5 years Pay Back
A13: 63 | B13: Rural | C13: PA | D13: 23647.52 | E13: 975 | F13: 350 | G13: 7500 | H13: 3.1530027 | I13: 1-5 years Pay Back
... A26: 399 | B26: Rural | C26: TX | D26: 25496.4 | E26: 950 | F26: 200 | G26: 9000 | H26: 2.8329333 | I26: 1-5 years Pay Back
A27: 6 | B27: Rural | C27: AZ | D27: 25682 | E27: 875 | G27: 10500 | H27: 2.4459048 | I27: 1-5 years Pay Back
A28: 357 | B28: Rural | C28: AZ | D28: 25762.8 | E28: 950 | F28: 250 | G28: 8400 | H28: 3.067 | I28: 1-5 years Pay Back
A29: 288 | B29: Rural | C29: PA | D29: 25816.8 | E29: 950 | F29: 325 | G29: 7500 | H29: 3.44224 | I29: 1-5 years Pay Back
A30: 60 | B30: Rural | C30: PA | D30: 26023.92 | E30: 975 | F30: 200 | G30: 9300 | H30: 2.798271 | I30: 1-5 years Pay Back
A31: 401 | B31: Rural | C31: OR | D31: 26030.4 | E31: 825 | F31: 350 | G31: 5700 | H31: 4.5667368 | I31: 1-5 years Pay Back
A32: 92 | B32: Rural | C32: AZ | D32: 26047.67 | E32: 975 | F32: 325 | G32: 7800 | H32: 3.3394449 | I32: 1-5 years Pay Back
A33: 465 | B33: Rural | C33: OR | D33: 26068.75 | E33: 950 | F33: 250 | G33: 8400 | H33: 3.1034226 | I33: 1-5 years Pay Back
A34: 150 | B34: Rural | C34: PA | D34: 26139.24 | E34: 950 | F34: 350 | G34: 7200 | H34: 3.63045 | I34: 1-5 years Pay Back
A35: 198 | B35: Rural | C35: PA | D35: 26142.48 | E35: 975 | F35: 175 | G35: 9600 | H35: 2.723175 | I35: 1-5 years Pay Back
A36: 208 | B36: Rural | C36: TX | D36: 26345.52 | E36: 825 | F36: 175 | G36: 7800 | H36: 3.3776308 | I36: 1-5 years Pay Back
A37: 87 | B37: Rural | C37: AZ | D37: 26408.17 | E37: 975 | F37: 350 | G37: 7500 | H37: 3.5210893 | I37: 1-5 years Pay Back
A38: 118 | B38: Rural | C38: PA | D38: 26424.3 | E38: 950 | F38: 325 | G38: 7500 | H38: 3.52324 | I38: 1-5 years Pay Back
A39: 311 | B39: Rural | C39: TX | D39: 26619.6 | E39: 875 | F39: 375 | G39: 6000 | H39: 4.4366 | I39: 1-5 years Pay Back
... A60: 88 | B60: Rural | C60: TX | D60: 28656.66 | E60: 950 | F60: 300 | G60: 7800 | H60: 3.6739308 | I60: 1-5 years Pay Back
A61: 413 | B61: Rural | C61: PA | D61: 28665.15 | E61: 825 | G61: 9900 | H61: 2.8954697 | I61: 1-5 years Pay Back
A62: 177 | B62: Rural | C62: OR | D62: 28757.8 | E62: 825 | F62: 325 | G62: 6000 | H62: 4.7929667 | I62: 1-5 years Pay Back
A63: 55 | B63: Rural | C63: TX | D63: 28861.63 | E63: 825 | F63: 325 | G63: 6000 | H63: 4.8102717 | I63: 1-5 years Pay Back
A64: 251 | B64: Rural | C64: FL | D64: 28901.96 | E64: 875 | F64: 150 | G64: 8700 | H64: 3.3220644 | I64: 1-5 years Pay Back
A65: 145 | B65: Rural | C65: FL | D65: 28924.22 | E65: 875 | F65: 325 | G65: 6600 | H65: 4.3824576 | I65: 1-5 years Pay Back
A66: 193 | B66: Rural | C66: PA | D66: 29115.02 | E66: 975 | F66: 325 | G66: 7800 | H66: 3.7326949 | I66: 1-5 years Pay Back
A67: 391 | B67: Rural | C67: OR | D67: 29400 | E67: 875 | F67: 325 | G67: 6600 | H67: 4.4545455 | I67: 1-5 years Pay Back
A68: 29 | B68: Rural | C68: PA | D68: 29622 | E68: 975 | F68: 350 | G68: 7500 | H68: 3.9496 | I68: 1-5 years Pay Back
A69: 323 | B69: Rural | C69: AZ | D69: 29636.4 | E69: 825 | F69: 200 | G69: 7500 | H69: 3.95152 | I69: 1-5 years Pay Back
A70: 254 | B70: Rural | C70: TX | D70: 29835.82 | E70: 950 | F70: 225 | G70: 8700 | H70: 3.4294046 | I70: 1-5 years Pay Back
A71: 427 | B71: Rural | C71: TX | D71: 29895.15 | E71: 950 | F71: 275 | G71: 8100 | H71: 3.6907593 | I71: 1-5 years Pay Back
A72: 491 | B72: Rural | C72: OR | D72: 29931.25 | E72: 875 | F72: 325 | G72: 6600 | H72: 4.5350379 | I72: 1-5 years Pay Back
A73: 321 | B73: Rural | C73: FL | D73: 30102 | E73: 950 | G73: 11400 | H73: 2.6405263 | I73: 1-5 years Pay Back
A74: 170 | B74: Rural | C74: FL | D74: 30138.48 | E74: 825 | F74: 250 | G74: 6900 | H74: 4.3678957 | I74: 1-5 years Pay Back
A75: 328 | B75: Rural | C75: PA | D75: 30178.8 | E75: 975 | F75: 300 | G75: 8100 | H75: 3.7257778 | I75: 1-5 years Pay Back
A76: 66 | B76: Rural | C76: FL | D76: 30245.28 | E76: 825 | F76: 400 | G76: 5100 | H76: 5.9304471 | I76: 5-10 years Pay Back
A77: 256 | B77: Rural | C77: PA | D77: 30325 | E77: 875 | F77: 350 | G77: 6300 | H77: 4.8134921 | I77: 1-5 years Pay Back
A78: 313 | B78: Rural | C78: PA | D78: 30336 | E78: 825 | F78: 325 | G78: 6000 | H78: 5.056 | I78: 5-10 years Pay Back
A79: 185 | B79: Rural | C79: TX | D79: 30366.88 | E79: 825 | F79: 325 | G79: 6000 | H79: 5.0611467 | I79: 5-10 years Pay Back
A80: 333 | B80: Rural | C80: FL | D80: 30398.4 | E80: 975 | F80: 350 | G80: 7500 | H80: 4.05312 | I80: 1-5 years Pay Back
A81: 209 | B81: Rural | C81: PA | D81: 30456.98 | E81: 825 | F81: 200 | G81: 7500 | H81: 4.0609307 | I81: 1-5 years Pay Back
A82: 192 | B82: Rural | C82: OR | D82: 30542.84 | E82: 950 | F82: 200 | G82: 9000 | H82: 3.3936489 | I82: 1-5 years Pay Back
A83: 247 | B83: Rural | C83: TX | D83: 30556.44 | E83: 825 | F83: 250 | G83: 6900 | H83: 4.4284696 | I83: 1-5 years Pay Back
A84: 227 | B84: Rural | C84: AZ | D84: 30646.08 | E84: 975 | F84: 325 | G84: 7800 | H84: 3.9289846 | I84: 1-5 years Pay Back
A85: 314 | B85: Rural | C85: AZ | D85: 30674.4 | E85: 950 | F85: 325 | G85: 7500 | H85: 4.08992 | I85: 1-5 years Pay Back
... A111: 466 | B111: Rural | C111: PA | D111: 32921.25 | E111: 975 | F111: 375 | G111: 7200 | H111: 4.5723958 | I111: 1-5 years Pay Back
A112: 105 | B112: Rural | C112: PA | D112: 33072.9 | E112: 825 | G112: 9900 | H112: 3.340697 | I112: 1-5 years Pay Back
A113: 352 | B113: Rural | C113: AZ | D113: 33214.8 | E113: 825 | F113: 175 | G113: 7800 | H113: 4.2583077 | I113: 1-5 years Pay Back
A114: 33 | B114: Rural | C114: OR | D114: 33341 | E114: 975 | F114: 325 | G114: 7800 | H114: 4.2744872 | I114: 1-5 years Pay Back
A115: 49 | B115: Rural | C115: AZ | D115: 33360.6 | E115: 950 | F115: 325 | G115: 7500 | H115: 4.44808 | I115: 1-5 years Pay Back
A116: 414 | B116: Rural | C116: PA | D116: 33428.94 | E116: 950 | F116: 350 | G116: 7200 | H116: 4.6429083 | I116: 1-5 years Pay Back
A117: 377 | B117: Rural | C117: PA | D117: 33474 | E117: 975 | F117: 300 | G117: 8100 | H117: 4.1325926 | I117: 1-5 years Pay Back
A118: 343 | B118: Rural | C118: FL | D118: 33500.4 | E118: 875 | F118: 150 | G118: 8700 | H118: 3.8506207 | I118: 1-5 years Pay Back
A119: 370 | B119: Rural | C119: OR | D119: 33554.4 | E119: 825 | F119: 350 | G119: 5700 | H119: 5.8867368 | I119: 5-10 years Pay Back
A120: 402 | B120: Rural | C120: OR | D120: 33697.2 | E120: 825 | F120: 325 | G120: 6000 | H120: 5.6162 | I120: 5-10 years Pay Back
A121: 326 | B121: Rural | C121: OR | D121: 33807.6 | E121: 875 | F121: 350 | G121: 6300 | H121: 5.3662857 | I121: 5-10 years Pay Back
A122: 365 | B122: Rural | C122: AZ | D122: 33969.6 | E122: 875 | F122: 175 | G122: 8400 | H122: 4.044 | I122: 1-5 years Pay Back
A123: 162 | B123: Rural | C123: PA | D123: 34003.74 | E123: 825 | G123: 9900 | H123: 3.4347212 | I123: 1-5 years Pay Back
A124: 255 | B124: Rural | C124: PA | D124: 34105 | E124: 825 | F124: 325 | G124: 6000 | H124: 5.6841667 | I124: 5-10 years Pay Back
A125: 17 | B125: Rural | C125: PA | D125: 34124 | E125: 875 | F125: 200 | G125: 8100 | H125: 4.2128395 | I125: 1-5 years Pay Back
A126: 474 | B126: Rural | C126: PA | D126: 34130 | E126: 825 | F126: 350 | G126: 5700 | H126: 5.9877193 | I126: 5-10 years Pay Back
A127: 157 | B127: Rural | C127: FL | D127: 34260.26 | E127: 875 | F127: 250 | G127: 7500 | H127: 4.5680347 | I127: 1-5 years Pay Back
A128: 183 | B128: Rural | C128: FL | D128: 34563.42 | E128: 975 | F128: 250 | G128: 8700 | H128: 3.9728069 | I128: 1-5 years Pay Back
A129: 424 | B129: Rural | C129: FL | D129: 34626.96 | E129: 950 | F129: 350 | G129: 7200 | H129: 4.8093 | I129: 1-5 years Pay Back
A130: 458 | B130: Rural | C130: AZ | D130: 34838.52 | E130: 975 | F130: 350 | G130: 7500 | H130: 4.645136 | I130: 1-5 years Pay Back
A131: 305 | B131: Rural | C131: TX | D131: 34915.2 | E131: 875 | F131: 275 | G131: 7200 | H131: 4.8493333 | I131: 1-5 years Pay Back
A132: 126 | B132: Rural | C132: TX | D132: 34934.42 | E132: 825 | F132: 350 | G132: 5700 | H132: 6.1288456 | I132: 5-10 years Pay Back
A133: 261 | B133: Rural | C133: AZ | D133: 35066.25 | E133: 825 | F133: 375 | G133: 5400 | H133: 6.49375 | I133: 5-10 years Pay Back
A134: 123 | B134: Rural | C134: TX | D134: 35134.56 | E134: 950 | F134: 150 | G134: 9600 | H134: 3.65985 | I134: 1-5 years Pay Back
A135: 199 | B135: Rural | C135: PA | D135: 35300.12 | E135: 950 | F135: 325 | G135: 7500 | H135: 4.7066827 | I135: 1-5 years Pay Back
... A145: 498 | B145: Rural | C145: PA | D145: 35860 | E145: 950 | F145: 225 | G145: 8700 | H145: 4.1218391 | I145: 1-5 years Pay Back
A146: 374 | B146: Rural | C146: PA | D146: 35860.8 | E146: 975 | G146: 11700 | H146: 3.0650256 | I146: 1-5 years Pay Back
A147: 82 | B147: Rural | C147: AZ | D147: 35933.04 | E147: 875 | F147: 225 | G147: 7800 | H147: 4.6068 | I147: 1-5 years Pay Back
A148: 371 | B148: Rural | C148: TX | D148: 35968.8 | E148: 825 | F148: 350 | G148: 5700 | H148: 6.3103158 | I148: 5-10 years Pay Back
A149: 128 | B149: Rural | C149: FL | D149: 36090.88 | E149: 825 | F149: 325 | G149: 6000 | H149: 6.0151467 | I149: 5-10 years Pay Back
A150: 468 | B150: Rural | C150: TX | D150: 36393.75 | E150: 825 | F150: 250 | G150: 6900 | H150: 5.2744565 | I150: 5-10 years Pay Back
A151: 228 | B151: Rural | C151: OR | D151: 36587.16 | E151: 950 | F151: 325 | G151: 7500 | H151: 4.878288 | I151: 1-5 years Pay Back
A152: 160 | B152: Rural | C152: OR | D152: 36601.4 | E152: 975 | F152: 275 | G152: 8400 | H152: 4.3573095 | I152: 1-5 years Pay Back
A153: 85 | B153: Rural | C153: TX | D153: 36601.95 | E153: 975 | F153: 325 | G153: 7800 | H153: 4.6925577 | I153: 1-5 years Pay Back
A154: 292 | B154: Rural | C154: TX | D154: 36832.8 | E154: 875 | F154: 275 | G154: 7200 | H154: 5.1156667 | I154: 5-10 years Pay Back
A155: 194 | B155: Rural | C155: OR | D155: 36980.28 | E155: 950 | F155: 350 | G155: 7200 | H155: 5.13615 | I155: 5-10 years Pay Back
A156: 312 | B156: Rural | C156: OR | D156: 37052.4 | E156: 950 | F156: 150 | G156: 9600 | H156: 3.859625 | I156: 1-5 years Pay Back
A157: 463 | B157: Rural | C157: PA | D157: 37098.75 | E157: 825 | F157: 300 | G157: 6300 | H157: 5.8886905 | I157: 5-10 years Pay Back
A158: 246 | B158: Rural | C158: PA | D158: 37101.06 | E158: 975 | F158: 375 | G158: 7200 | H158: 5.152925 | I158: 5-10 years Pay Back
... A199: 306 | B199: Rural | C199: FL | D199: 40851.6 | E199: 825 | F199: 150 | G199: 8100 | H199: 5.0434074 | I199: 5-10 years Pay Back
A200: 100 | B200: Rural | C200: TX | D200: 40964.56 | E200: 875 | G200: 10500 | H200: 3.9013867 | I200: 1-5 years Pay Back
A201: 309 | B201: Rural | C201: TX | D201: 41137.2 | E201: 875 | F201: 300 | G201: 6900 | H201: 5.961913 | I201: 5-10 years Pay Back
A202: 432 | B202: Rural | C202: FL | D202: 41217.3 | E202: 825 | F202: 275 | G202: 6600 | H202: 6.2450455 | I202: 5-10 years Pay Back
A203: 346 | B203: Rural | C203: TX | D203: 41354.4 | E203: 875 | F203: 275 | G203: 7200 | H203: 5.7436667 | I203: 5-10 years Pay Back
A204: 289 | B204: Rural | C204: PA | D204: 41454 | E204: 875 | F204: 325 | G204: 6600 | H204: 6.2809091 | I204: 5-10 years Pay Back
A205: 460 | B205: Rural | C205: TX | D205: 41480.52 | E205: 975 | F205: 150 | G205: 9900 | H205: 4.1899515 | I205: 1-5 years Pay Back
A206: 231 | B206: Rural | C206: TX | D206: 41497.94 | E206: 875 | F206: 250 | G206: 7500 | H206: 5.5330587 | I206: 5-10 years Pay Back
...

Sheet OLDExecutive_Dashboard
D36: Pillar / Strategic Area | F36: Key Metric & Insight | I36: Risk / Opportunity | L36: Recommendation
D37: Pillar 1: Density & Growth | F37: 44.1% High Potential (187 sites) concentrated in Urban/Suburban hubs. | I37: Opportunity: High demand density and carrier network densification needs. | L37: Prioritize sales outreach & fast-track co-location leasing in Top Urban markets.
D38: Pillar 2: Structural Profile | F38: Monopole dominance (~60%) with structural capacity for 2–3 additional tenancy slots. | I38: Risk: Overloading existing structural limits without CapEx upgrades. | L38: Standardize structural modifications (RAD center extensions) for rapid carrier mounting.
D39: Pillar 3: Financial Profile | F39: Avg. CapEx per site: ~$308K; 68% of inventory falls in the 5–10 Year Payback tranche. | I39: Opportunity: High-potential sites yield accelerated ROI (12.6 yrs payback). | L39: Direct capital allocation toward sites with immediate multi-tenant leasing potential.
D40: Pillar 4: Age Profile | F40: Peak construction (2015–2019)accounts for the largest cohort of unleased assets. | I40: Risk: Aging structural assets may require deferred maintenance before tenancy. | L40: Audit 10+ year vintage sites for structural integrity during tenancy onboarding.
